Workbook

Sheet TB @ 30 Sept 2025
A1: Hunt3X Corporation
A2: Trial Balance as at 30 September 2025 | B2: Debit | C2: Credit
A3: Cash | B3: 387216
A4: Accounts Receivable | B4: 37100
A5: Prepaid Rent | B5: =2200*9 -> 19800
A6: Inventory | B6: 84000
A7: Accounts Payable | C7: 23400
A8: Unearned Revenue | C8: 14500
A9: Long-term Debt | C9: 50000
A10: Share Capital - Ordinary Shares | C10: 200000
A11: Share Capital - Preference Shares (cumulative) | C11: 200000
A12: Retained Earnings (@ 31 Dec 2024) | C12: 5230
A13: Sales Revenue | C13: 212300
A14: Cost of Goods Sold | B14: =C13*0.38 -> 80674
A15: Rent Expense | B15: =2200*3 -> 6600
A16: Marketing Expense | B16: 13000
A17: Salaries Expense | B17: =7700*9 -> 69300
A18: General Admin Expense | B18: =860*9 -> 7740
B19: =SUM(B3:B18) -> 705430 | C19: =SUM(C3:C18) -> 705430
A20: NI | B20: =C13-SUM(B14:B18) -> 34986

Sheet Tutorial 2 Sol
A1: TUTORIAL 2 SOLUTION
A2: PART (1) | H2: PART (2) | N2: Part (3) | W2: PART (4)
A3: Accounting Equation Effects | H3: Journal Entries | K3: Debit | L3: Credit | N3: Trial Balance Worksheet | W3: Total Liabilities | X3: =D22 -> 116350
B4: Assets | C4: = | D4: Liabilities | E4: + | F4: Equity | N4: Account Name | O4: @ 30 September 2025 | Q4: Transactions (Sept - Dec) | T4: @ 31 Dec 2025 | W4: Total Assets | X4: =B22 -> 831396
A5: Balance @ 30 Sept 2025 | B5: =SUM('TB @ 30 Sept 2025'!B3:B6) -> 528116 | C5: =C4 -> = | D5: =SUM('TB @ 30 Sept 2025'!C7:C9) -> 87900 | E5: =E4 -> + | F5: =SUM('TB @ 30 Sept 2025'!C10:C18)-SUM('TB @ 30 Sept 2025'!B10:B18) -> 440216 | G5: =B5-D5-F5 -> 0 | H5: (a) | I5: Cash | K5: 250000 | O5: Debit | P5: Credit | Q5: Ref | R5: Debit | S5: Credit | T5: Debit | U5: Credit | W5: Debt Ratio | X5: =X3/X4 -> 0.13994534
A6: =H5 -> (a) | B6: =K5 -> 250000 | C6: =C5 -> = | E6: =E5 -> + | F6: =L6 -> 250000 | J6: Share Capital - Ordinary Shares | L6: =K5 -> 250000 | N6: ='TB @ 30 Sept 2025'!A3 -> Cash | O6: ='TB @ 30 Sept 2025'!B3 -> 387216 | Q6: =H5 -> (a) | R6: =K5 -> 250000 | T6: =O6+SUM(R6:R15)-SUM(S6:S15) -> 359516
A7: =H8 -> (b) | B7: =K8 -> 30000 | C7: =C6 -> = | D7: =L9 -> 30000 | E7: =E6 -> + | Q7: =H8 -> (b) | R7: =K8 -> 30000 | W7: Beginning Total Assets | X7: ='TB @ 31 Dec 2024'!B13 -> 473830
A8: =H11 -> (c) | B8: =K11 -> 65000 | C8: =C7 -> = | E8: =E7 -> + | H8: (b) | I8: Cash | K8: 30000 | Q8: =H11 -> (c) | S8: =L12 -> 65000
B9: =-L12 -> -65000 | C9: =C8 -> = | E9: =E8 -> + | J9: Short Term Notes Payable | L9: =K8 -> 30000 | Q9: =H14 -> (d) | R9: =K14 -> 35000 | W9: Net Profit | X9: =U30-(SUM(T31:T35)) -> 59816
A10: =H14 -> (d) | B10: =K14 -> 35000 | C10: =C8 -> = | E10: =E8 -> + | F10: =L16 -> 96000 | Q10: =H21 -> (e) | R10: =K21 -> 64300 | W10: Average Total Assets | X10: =(X4+X7)/2 -> 652613
B11: =K15 -> 61000 | H11: (c) | I11: Inventory | K11: 65000 | Q11: =H24 -> (f) | S11: =L25 -> 22300 | W11: Return on Assets | X11: =X9/X10 -> 0.091656158
B12: =-L19 -> -30720 | C12: =C10 -> = | E12: =E10 -> + | F12: =-K18 -> -30720 | J12: Cash | L12: =K11 -> 65000 | Q12: =H27 -> (g) | S12: =L28 -> 19200
A13: =H21 -> (e) | B13: =K21 -> 64300 | C13: =C12 -> = | E13: =E12 -> + | Q13: =H30 -> (h) | S13: =L31 -> 300000
B14: =-L22 -> -64300 | C14: =C13 -> = | E14: =E13 -> + | H14: (d) | I14: Cash | K14: 35000 | Q14: =H33 -> (i) | S14: =L34 -> 5500
A15: =H24 -> (f) | B15: =-L25 -> -22300 | C15: =C14 -> = | E15: =E14 -> + | F15: =-K24 -> -22300 | I15: Accounts Receivable | K15: =L16-K14 -> 61000 | Q15: =H36 -> (j) | R15: =K36 -> 5000
A16: =H27 -> (g) | B16: =-L28 -> -19200 | C16: =C15 -> = | D16: =-K27 -> -19200 | E16: =E15 -> + | J16: Sales Revenue | L16: 96000 | N16: ='TB @ 30 Sept 2025'!A4 -> Accounts Receivable | O16: ='TB @ 30 Sept 2025'!B4 -> 37100 | Q16: =H14 -> (d) | R16: =K15 -> 61000 | T16: =O16+SUM(R16:R17)-SUM(S16:S17) -> 33800
A17: =H30 -> (h) | B17: =K30 -> 300000 | C17: =C16 -> = | E17: =E16 -> + | Q17: =H21 -> (e) | S17: =L22 -> 64300
B18: =-L31 -> -300000 | C18: =C17 -> = | E18: =E17 -> + | I18: Cost of Goods Sold | K18: =L16*0.32 -> 30720 | N18: ='TB @ 30 Sept 2025'!A5 -> Prepaid Rent | O18: ='TB @ 30 Sept 2025'!B5 -> 19800 | T18: =O18+R18-S18 -> 19800
A19: =H33 -> (i) | B19: -5500 | C19: =C18 -> = | E19: =E18 -> + | F19: =-K33 -> -5500 | J19: Inventory | L19: =K18 -> 30720 | N19: ='TB @ 30 Sept 2025'!A6 -> Inventory | O19: ='TB @ 30 Sept 2025'!B6 -> 84000 | Q19: =H11 -> (c) | R19: =K11 -> 65000 | T19: =O19+SUM(R19:R20)-SUM(S19:S20) -> 118280
A20: =H36 -> (j) | B20: =K36 -> 5000 | C20: =C19 -> = | D20: =L37 -> 5000 | Q20: =H14 -> (d) | S20: =L19 -> 30720
A21: =H39 -> (k) | C21: =C20 -> = | D21: =L40 -> 12650 | F21: =-K39 -> -12650 | H21: (e) | I21: Cash | K21: 64300 | N21: Property Plant and Equipment (PPE) | O21: 0 | Q21: =H30 -> (h) | R21: =K30 -> 300000 | T21: =O21+R21-S21 -> 300000
A22: Balance @ 31 Dec 2025 | B22: =SUM(B5:B21) -> 831396 | C22: = | D22: =SUM(D5:D21) -> 116350 | E22: + | F22: =SUM(F5:F21) -> 715046 | J22: Accounts Receivable | L22: =K21 -> 64300 | N22: ='TB @ 30 Sept 2025'!A7 -> Accounts Payable | P22: ='TB @ 30 Sept 2025'!C7 -> 23400 | Q22: =H27 -> (g) | R22: =K27 -> 19200 | U22: =P22+SUM(S22:S23)-SUM(R22:R23) -> 16850
Q23: =H39 -> (k) | S23: =L40 -> 12650
A24: Balance Check | B24: =SUM(T6:T21) -> 831396 | D24: =SUM(U22:U26) -> 116350 | F24: =SUM(U27:U36)-SUM(T27:T36) -> 715046 | H24: (f) | I24: Salaries Expense | K24: 22300 | N24: ='TB @ 30 Sept 2025'!A8 -> Unearned Revenue | P24: ='TB @ 30 Sept 2025'!C8 -> 14500 | Q24: =H36 -> (j) | S24: =L37 -> 5000 | U24: =P24+S24-R24 -> 19500
B25: =B22-B24 -> 0 | D25: =D22-D24 -> 0 | F25: =F22-F24 -> 0 | J25: Cash | L25: =K24 -> 22300 | N25: Short Term Notes Payable | P25: 0 | Q25: =H8 -> (b) | S25: =L9 -> 30000 | U25: =P25+S25-R25 -> 30000
N26: ='TB @ 30 Sept 2025'!A9 -> Long-term Debt | P26: ='TB @ 30 Sept 2025'!C9 -> 50000 | U26: =P26+S26-R26 -> 50000
H27: (g) | I27: Accounts Payable | K27: 19200 | N27: ='TB @ 30 Sept 2025'!A10 -> Share Capital - Ordinary Shares | P27: ='TB @ 30 Sept 2025'!C10 -> 200000 | Q27: =Q6 -> (a) | S27: =L6 -> 250000 | U27: =P27+S27-R27 -> 450000
J28: Cash | L28: =K27 -> 19200 | N28: ='TB @ 30 Sept 2025'!A11 -> Share Capital - Preference Shares (cumulative) | P28: ='TB @ 30 Sept 2025'!C11 -> 200000 | U28: =P28+S28-R28 -> 200000
N29: ='TB @ 30 Sept 2025'!A12 -> Retained Earnings (@ 31 Dec 2024) | P29: ='TB @ 30 Sept 2025'!C12 -> 5230 | U29: =P29+S29-R29 -> 5230
H30: (h) | I30: Property Plant and Equipment (PPE) | K30: 300000 | N30: ='TB @ 30 Sept 2025'!A13 -> Sales Revenue | P30: ='TB @ 30 Sept 2025'!C13 -> 212300 | Q30: =Q16 -> (d) | S30: =L16 -> 96000 | U30: =P30+S30-R30 -> 308300
J31: Cash | L31: =K30 -> 300000 | N31: ='TB @ 30 Sept 2025'!A14 -> Cost of Goods Sold | O31: ='TB @ 30 Sept 2025'!B14 -> 80674 | Q31: =Q30 -> (d) | R31: =K18 -> 30720 | T31: =O31+R31-S31 -> 111394
N32: ='TB @ 30 Sept 2025'!A15 -> Rent Expense | O32: ='TB @ 30 Sept 2025'!B15 -> 6600 | T32: =O32+R32-S32 -> 6600
H33: (i) | I33: Marketing Expense | K33: 5500 | N33: ='TB @ 30 Sept 2025'!A16 -> Marketing Expense | O33: ='TB @ 30 Sept 2025'!B16 -> 13000 | Q33: =H33 -> (i) | R33: =K33 -> 5500 | T33: =O33+R33-S33 -> 18500
J34: Cash | L34: =K33 -> 5500 | N34: ='TB @ 30 Sept 2025'!A17 -> Salaries Expense | O34: ='TB @ 30 Sept 2025'!B17 -> 69300 | Q34: =H24 -> (f) | R34: =K24 -> 22300 | T34: =O34+R34-S34 -> 91600
N35: ='TB @ 30 Sept 2025'!A18 -> General Admin Expense | O35: ='TB @ 30 Sept 2025'!B18 -> 7740 | Q35: =H39 -> (k) | R35: =K39 -> 12650 | T35: =O35+R35-S35 -> 20390
H36: (j) | I36: Cash | K36: 5000
J37: Unearned Revenue | L37: =K36 -> 5000 | O37: =SUM(O6:O36) -> 705430 | P37: =SUM(P6:P36) -> 705430 | R37: =SUM(R6:R36) -> 900670 | S37: =SUM(S6:S36) -> 900670 | T37: =SUM(T6:T36) -> 1079880 | U37: =SUM(U6:U36) -> 1079880
H39: (k) | I39: General Admin Expense | K39: 12650
J40: Accounts Payable | L40: =K39 -> 12650
K41: =SUM(K4:K37) -> 888020 | L41: =SUM(L4:L37) -> 888020

Sheet Tutorial 3 Sol
A1: TUTORIAL 3 SOLUTION
A3: Adjusting / Correcting Journal Entries | D3: Debit | E3: Credit
A5: (a) | B5: Rent Expense | D5: =26400/12*3 -> 6600
C6: Prepaid Rent | E6: =D5 -> 6600
A8: (b) | B8: Unearned Revenue | D8: =14500/2 -> 7250
C9: Sales Revenue | E9: =D8 -> 7250
B11: Cost of Goods Sold | D11: 2540
C12: Inventory | E12: =D11 -> 2540
A14: (c) | B14: Interest Expense | D14: 2850
C15: Interest Payable | E15: =D14 -> 2850
A17: (d) | B17: Consulting Fees | D17: =450*4 -> 1800
C18: Consulting Fees Payable | E18: =D17 -> 1800
A20: (e) | B20: Depreciation Expense | D20: 8200
C21: Accumulated Depreciation - Equipment | E21: =D20 -> 8200
A23: (f) | B23: Prepaid Salaries | D23: 2200
C24: Salaries Expense | E24: =D23 -> 2200
A26: (g) | B26: Income Tax Expense | D26: 4200
C27: Taxes Payable | E27: =D26 -> 4200
D28: =SUM(D4:D27) -> 35640 | E28: =SUM(E4:E27) -> 35640

Sheet TB @ 31 Dec 2024
A1: Hunt3X Corporation
A2: Account Balances as at 31 Dec 2024 | B2: Debit | C2: Credit
A3: ='TB @ 30 Sept 2025'!A3 -> Cash | B3: 350130
A4: ='TB @ 30 Sept 2025'!A4 -> Accounts Receivable | B4: 21700
A5: ='TB @ 30 Sept 2025'!A6 -> Inventory | B5: 102000
A6: ='TB @ 30 Sept 2025'!A7 -> Accounts Payable | C6: 18600
A7: ='TB @ 30 Sept 2025'!A9 -> Long-term Debt | C7: ='TB @ 30 Sept 2025'!C9 -> 50000
A8: ='TB @ 30 Sept 2025'!A10 -> Share Capital - Ordinary Shares | C8: ='TB @ 30 Sept 2025'!C10 -> 200000
A9: ='TB @ 30 Sept 2025'!A11 -> Share Capital - Preference Shares (cumulative) | C9: ='TB @ 30 Sept 2025'!C11 -> 200000
A10: ='TB @ 30 Sept 2025'!A12 -> Retained Earnings (@ 31 Dec 2024) | C10: ='TB @ 30 Sept 2025'!C12 -> 5230
B11: =SUM(B3:B10) -> 473830 | C11: =SUM(C3:C10) -> 473830
A13: Total Assets | B13: =SUM(B3:B5) -> 473830
A14: Total Liabilities | C14: =SUM(C6:C7) -> 68600
A15: Total Equity | C15: =SUM(C8:C10) -> 405230
